omicvarsel/__init__.py
omicvarsel/cli.py
omicvarsel/omicvarsel.py
omicvarsel-0.1.0.dist-info/AUTHORS.rst
omicvarsel-0.1.0.dist-info/LICENSE
omicvarsel-0.1.0.dist-info/METADATA
omicvarsel-0.1.0.dist-info/WHEEL
omicvarsel-0.1.0.dist-info/entry_points.txt
omicvarsel-0.1.0.dist-info/top_level.txt
omicvarsel-0.1.0.dist-info/RECORD
